LICENSE
MANIFEST.in
README.md
setup.py
accounts/__init__.py
accounts/abstract_models.py
accounts/admin.py
accounts/codes.py
accounts/core.py
accounts/exceptions.py
accounts/facade.py
accounts/forms.py
accounts/models.py
accounts/names.py
accounts/security.py
accounts/views.py
accounts/api/__init__.py
accounts/api/app.py
accounts/api/decorators.py
accounts/api/errors.py
accounts/api/views.py
accounts/checkout/__init__.py
accounts/checkout/allocation.py
accounts/checkout/forms.py
accounts/checkout/gateway.py
accounts/dashboard/__init__.py
accounts/dashboard/app.py
accounts/dashboard/forms.py
accounts/dashboard/reports.py
accounts/dashboard/views.py
accounts/management/__init__.py
accounts/management/commands/__init__.py
accounts/management/commands/close_expired_accounts.py
accounts/migrations/0001_initial.py
accounts/migrations/__init__.py
accounts/migrations/bak-0001_initial.py
accounts/migrations/fb-0001_initial.py
accounts/templates/accounts/balance_check.html
accounts/templates/accounts/dashboard/account_detail.html
accounts/templates/accounts/dashboard/account_form.html
accounts/templates/accounts/dashboard/account_freeze.html
accounts/templates/accounts/dashboard/account_list.html
accounts/templates/accounts/dashboard/account_thaw.html
accounts/templates/accounts/dashboard/account_top_up.html
accounts/templates/accounts/dashboard/transfer_detail.html
accounts/templates/accounts/dashboard/transfer_list.html
accounts/templates/accounts/dashboard/partials/account_detail.html
accounts/templates/accounts/dashboard/reports/deferred_income.html
accounts/templates/accounts/dashboard/reports/profit_loss.html
django_account_balances.egg-info/PKG-INFO
django_account_balances.egg-info/SOURCES.txt
django_account_balances.egg-info/dependency_links.txt
django_account_balances.egg-info/requires.txt
django_account_balances.egg-info/top_level.txt