Metadata-Version: 1.1
Name: django-account-balances
Version: 0.4
Summary: Track account credits in Django
Home-page: UNKNOWN
Author: Jason Carver
Author-email: jason@membright.com
License: Copyright (c) 2011, Tangent Communications PLC and individual contributors.
